dogsheep_photos/__init__.py
dogsheep_photos/cli.py
dogsheep_photos/utils.py
dogsheep_photos-0.4.1.dist-info/LICENSE
dogsheep_photos-0.4.1.dist-info/METADATA
dogsheep_photos-0.4.1.dist-info/WHEEL
dogsheep_photos-0.4.1.dist-info/entry_points.txt
dogsheep_photos-0.4.1.dist-info/top_level.txt
dogsheep_photos-0.4.1.dist-info/RECORD
