Metadata-Version: 2.1
Name: dogsheep-photos
Version: 0.4.1
Summary: Save details of your photos to a SQLite database and upload them to S3
Home-page: https://github.com/dogsheep/dogsheep-photos
Author: Simon Willison
License: Apache License, Version 2.0
Platform: UNKNOWN
Requires-Dist: sqlite-utils (>=2.7)
Requires-Dist: boto3 (>=1.12.41)
Requires-Dist: osxphotos (>=0.28.13) ; sys_platform == "darwin"
Provides-Extra: test
Requires-Dist: pytest ; extra == 'test'
